lovely_grad/__init__.py
lovely_grad/_modidx.py
lovely_grad/patch.py
lovely_grad/repr_chans.py
lovely_grad/repr_plt.py
lovely_grad/repr_rgb.py
lovely_grad/repr_str.py
lovely_grad/utils/__init__.py
lovely_grad/utils/config.py
lovely_grad/utils/misc.py
lovely_grad-0.0.4.dist-info/licenses/LICENSE
lovely_grad-0.0.4.dist-info/METADATA
lovely_grad-0.0.4.dist-info/WHEEL
lovely_grad-0.0.4.dist-info/entry_points.txt
lovely_grad-0.0.4.dist-info/top_level.txt
lovely_grad-0.0.4.dist-info/RECORD
