Metadata-Version: 2.4
Name: lovely-grad
Version: 0.0.4
Summary: 🫀 Lovely Grad - tiny tensors need some love
Home-page: https://github.com/xl0/lovely-grad
Author: Alexey
Author-email: alexey.zaytsev@gmail.com
License: MIT License
Keywords: nbdev jupyter notebook python
Classifier: Development Status :: 4 - Beta
Classifier: Intended Audience :: Developers
Classifier: Natural Language :: English
Classifier: Programming Language :: Python :: 3.10
Classifier: Programming Language :: Python :: 3.11
Classifier: Programming Language :: Python :: 3.12
Classifier: Programming Language :: Python :: 3.13
Classifier: License :: OSI Approved :: MIT License
Requires-Python: >=3.10
License-File: LICENSE
Requires-Dist: lovely-numpy
Requires-Dist: tinygrad
Provides-Extra: dev
Requires-Dist: nbdev; extra == "dev"
Requires-Dist: python-dotenv; extra == "dev"
Dynamic: author
Dynamic: author-email
Dynamic: classifier
Dynamic: description
Dynamic: description-content-type
Dynamic: home-page
Dynamic: keywords
Dynamic: license
Dynamic: license-file
Dynamic: provides-extra
Dynamic: requires-dist
Dynamic: requires-python
Dynamic: summary
